odoo/addons/hr_attendance_autoclose/README.rst
odoo/addons/hr_attendance_autoclose/__init__.py
odoo/addons/hr_attendance_autoclose/__manifest__.py
odoo/addons/hr_attendance_autoclose/data/hr_attendance.xml
odoo/addons/hr_attendance_autoclose/data/hr_attendance_reason.xml
odoo/addons/hr_attendance_autoclose/data/res_company.xml
odoo/addons/hr_attendance_autoclose/i18n/es.po
odoo/addons/hr_attendance_autoclose/i18n/fr.po
odoo/addons/hr_attendance_autoclose/i18n/hr.po
odoo/addons/hr_attendance_autoclose/i18n/hr_attendance_autoclose.pot
odoo/addons/hr_attendance_autoclose/i18n/it.po
odoo/addons/hr_attendance_autoclose/i18n/tr.po
odoo/addons/hr_attendance_autoclose/models/__init__.py
odoo/addons/hr_attendance_autoclose/models/hr_attendance.py
odoo/addons/hr_attendance_autoclose/models/hr_employee.py
odoo/addons/hr_attendance_autoclose/models/res_company.py
odoo/addons/hr_attendance_autoclose/models/res_config_settings.py
odoo/addons/hr_attendance_autoclose/readme/CONTRIBUTORS.md
odoo/addons/hr_attendance_autoclose/readme/DESCRIPTION.md
odoo/addons/hr_attendance_autoclose/readme/USAGE.md
odoo/addons/hr_attendance_autoclose/static/description/icon.png
odoo/addons/hr_attendance_autoclose/static/description/index.html
odoo/addons/hr_attendance_autoclose/tests/__init__.py
odoo/addons/hr_attendance_autoclose/tests/test_hr_attendance_auto_close.py
odoo/addons/hr_attendance_autoclose/views/hr_attendance_view.xml
odoo/addons/hr_attendance_autoclose/views/hr_employee.xml
odoo/addons/hr_attendance_autoclose/views/res_config_settings_view.xml
odoo_addon_hr_attendance_autoclose-17.0.1.0.0.6.dist-info/METADATA
odoo_addon_hr_attendance_autoclose-17.0.1.0.0.6.dist-info/WHEEL
odoo_addon_hr_attendance_autoclose-17.0.1.0.0.6.dist-info/top_level.txt
odoo_addon_hr_attendance_autoclose-17.0.1.0.0.6.dist-info/RECORD
